odoo/addons/website_sale_product_assortment/README.rst
odoo/addons/website_sale_product_assortment/__init__.py
odoo/addons/website_sale_product_assortment/__manifest__.py
odoo/addons/website_sale_product_assortment/controllers/__init__.py
odoo/addons/website_sale_product_assortment/controllers/variant.py
odoo/addons/website_sale_product_assortment/controllers/website_sale.py
odoo/addons/website_sale_product_assortment/i18n/es.po
odoo/addons/website_sale_product_assortment/i18n/website_sale_product_assortment.pot
odoo/addons/website_sale_product_assortment/models/__init__.py
odoo/addons/website_sale_product_assortment/models/ir_filters.py
odoo/addons/website_sale_product_assortment/models/product_template.py
odoo/addons/website_sale_product_assortment/readme/CONFIGURE.rst
odoo/addons/website_sale_product_assortment/readme/CONTRIBUTORS.rst
odoo/addons/website_sale_product_assortment/readme/DESCRIPTION.rst
odoo/addons/website_sale_product_assortment/static/description/icon.png
odoo/addons/website_sale_product_assortment/static/description/index.html
odoo/addons/website_sale_product_assortment/static/src/js/assortment_list_preview.js
odoo/addons/website_sale_product_assortment/static/src/js/no_purchase_tour.js
odoo/addons/website_sale_product_assortment/static/src/js/no_restriction_tour.js
odoo/addons/website_sale_product_assortment/static/src/js/no_show_tour.js
odoo/addons/website_sale_product_assortment/static/src/js/variant_mixin.js
odoo/addons/website_sale_product_assortment/static/src/xml/website_sale_product_assortment.xml
odoo/addons/website_sale_product_assortment/templates/assets.xml
odoo/addons/website_sale_product_assortment/templates/website_sale_views.xml
odoo/addons/website_sale_product_assortment/tests/__init__.py
odoo/addons/website_sale_product_assortment/tests/test_ui.py
odoo/addons/website_sale_product_assortment/views/ir_filters_views.xml
odoo13_addon_website_sale_product_assortment-13.0.1.0.1.dev7.dist-info/METADATA
odoo13_addon_website_sale_product_assortment-13.0.1.0.1.dev7.dist-info/WHEEL
odoo13_addon_website_sale_product_assortment-13.0.1.0.1.dev7.dist-info/top_level.txt
odoo13_addon_website_sale_product_assortment-13.0.1.0.1.dev7.dist-info/RECORD
